Workbook

Sheet Read me
A1: Use Case 13: Private RAG Assistant for Banking
A2: Evaluation question set, SPG Innovation Challenge 2026
A4: Purpose
A5: Use these questions to measure how well your assistant answers. Target: at least 85% accuracy on the question set.
A7: How to score an answer
A8: 1 = correct: covers the key points in the expected answer and contains no wrong statement.
A9: 0.5 = partly correct: some key points missing, nothing wrong or invented.
A10: 0 = wrong, missing, or contains invented facts, numbers or sources.
A11: Out-of-scope questions score 1 only if the assistant states that the corpus does not cover the question and invents nothing.
A13: Sources
A14: An answer counts as cited when it names the document and the section or article it relies on, and that passage actually supports the statement. Aim for at least two cited passages per answer wherever the corpus offers them.
A16: Things to know
... A23: Scoring: paste your assistant's answers, enter the scores (yellow cells), accuracy is calculated automatically.

Sheet Question set
A1: ID | B1: Topic | C1: Question | D1: Type | E1: Difficulty (1-3) | F1: Expected answer (key points) | G1: Expected source(s) | H1: Key terms (DE)
A2: Q01 | B2: Money laundering / KYC | C2: Under the German Money Laundering Act, in which situations must a bank carry out customer due diligence? | D2: Fact | E2: 1 | F2: 1) When establishing a business relationship. 2) For transactions outside an existing business relationship from EUR 15,000 (lower thresholds apply to transfers of funds). 3) When facts indicate money laundering or terrorist financing. 4) When there are doubts about the identity information provided. | G2: 01_GwG.pdf, section 10(3) | H2: Allgemeine Sorgfaltspflichten, Geschäftsbeziehung, Transaktion
A3: Q02 | B3: Money laundering / KYC | C3: When is a natural person considered the beneficial owner of a company under the GwG? | D3: Fact | E3: 1 | F3: A natural person who directly or indirectly holds more than 25% of the capital or voting rights, or exercises control in a comparable way. If no such person can be identified, the legal representative or managing director is treated as fictitious beneficial owner. | G3: 01_GwG.pdf, section 3(2) | H3: wirtschaftlich Berechtigter, fiktiver wirtschaftlich Berechtigter
A4: Q03 | B4: Money laundering / KYC | C4: How long must a bank retain the records it collects under its due diligence obligations? | D4: Fact | E4: 1 | F4: At least five years, and destroyed no later than ten years. The period starts at the end of the calendar year in which the business relationship ends (or the transaction is carried out). | G4: 01_GwG.pdf, section 8(4) | H4: Aufzeichnungs- und Aufbewahrungspflicht
A5: Q04 | B5: Money laundering / KYC | C5: A bank employee suspects that a customer payment is linked to money laundering. To whom must the bank report, and how quickly? | D5: Multi-document | E5: 2 | F5: Report to the Financial Intelligence Unit (FIU) without delay (unverzüglich), regardless of the amount involved. BaFin/FIU guidance explains that the report must be filed promptly once the facts indicating suspicion are known, and must be complete. | G5: 01_GwG.pdf, section 43(1); 10_BaFin_FIU_Verdachtsmeldungen.pdf | H5: Verdachtsmeldung, unverzüglich, FIU
A6: Q05 | B6: Money laundering / KYC | C6: After filing a suspicious activity report, may the bank execute the reported transaction straight away? | D6: Fact | E6: 2 | F6: No. The transaction may only be executed with the consent of the FIU or the public prosecutor, or once the third working day after the report was sent has passed without the transaction being prohibited (Saturdays do not count as working days). Exception: if postponing is impossible or would hinder the investigation, the bank may execute and report immediately afterwards. | G6: 01_GwG.pdf, section 46 | H6: Fristfall, dritter Werktag, Durchführung von Transaktionen
A7: Q06 | B7: Money laundering / KYC | C7: May a bank tell its customer that it has filed a suspicious activity report about them? | D7: Fact | E7: 1 | F7: No. The prohibition of disclosure (tipping off) forbids informing the customer or third parties about a planned or filed report or a resulting investigation. Narrow exceptions exist, e.g. for information to authorities and certain information sharing within the group. | G7: 01_GwG.pdf, section 47 | H7: Verbot der Informationsweitergabe
A8: Q07 | B8: Money laundering / KYC | C8: Which enhanced due diligence measures apply when the customer is a politically exposed person (PEP)? | D8: Multi-document | E8: 2 | F8: 1) Approval by senior management to establish or continue the relationship. 2) Measures to establish the source of wealth and source of funds. 3) Enhanced ongoing monitoring of the business relationship. EBA risk factor guidelines describe further risk factors and measures. | G8: 01_GwG.pdf, section 15(3) and (4); 04_EBA_Risikofaktoren.pdf | H8: politisch exponierte Person, verstärkte Sorgfaltspflichten, Herkunft der Vermögenswerte
A9: Q08 | B9: Money laundering / KYC | C9: Which document determines whether a country is a high-risk third country, and what does that mean for a German bank? | D9: Multi-document | E9: 2 | F9: The EU list in Delegated Regulation (EU) 2016/1675 (latest consolidated version, the list changes over time). For business relationships or transactions involving such countries, the GwG requires enhanced due diligence measures. | G9: 12_EU_Hochrisikodrittstaaten.pdf; 01_GwG.pdf, section 15(3) and (5) | H9: Drittstaat mit hohem Risiko, verstärkte Sorgfaltspflichten
A10: Q09 | B10: Money laundering / KYC | C10: Who in a bank must be responsible for AML/CFT, and at which level? | D10: Multi-document | E10: 2 | F10: A money laundering officer (Geldwäschebeauftragter) at management level plus a deputy must be appointed (GwG). EBA guidelines additionally require a member of the management body to be responsible for AML/CFT and an AML/CFT compliance officer with sufficient seniority, resources and direct reporting line. | G10: 01_GwG.pdf, section 7(1); 05_EBA_AML_Compliance_Officer.pdf | H10: Geldwäschebeauftragter, Führungsebene, Stellvertreter
A11: Q10 | B11: Money laundering / KYC | C11: What must a bank do before it starts using a remote customer onboarding solution? | D11: Fact | E11: 2 | F11: Have documented policies and procedures for remote onboarding and carry out a pre-implementation assessment of the solution (adequacy, reliability of data and documents, risks). After going live the solution must be monitored and reviewed on an ongoing basis. | G11: 06_EBA_Remote_Onboarding.pdf | H11: Fernidentifizierung, Bewertung vor Einführung
A12: Q11 | B12: Money laundering / KYC | C12: Which information about the payer and the payee must accompany a transfer of funds? | D12: Fact | E12: 2 | F12: Payer: name, payment account number, address including country, official personal document number, customer identification number or date and place of birth, and the LEI where available. Payee: name, payment account number and LEI where available. Simplified rules apply within the EU. | G12: 09_EU_Geldtransfer_2023_1113.pdf, Article 4 (and 5, 6) | H12: Angaben zum Auftraggeber, Angaben zum Begünstigten
A13: Q12 | B13: Sanctions | C13: What does an asset freeze under the EU Russia/Ukraine sanctions mean for a bank holding an account of a listed person? | D13: Fact | E13: 1 | F13: All funds and economic resources belonging to, owned, held or controlled by the listed person must be frozen. In addition, no funds or economic resources may be made available to the listed person, directly or indirectly. | G13: 14_EU_Sanktionen_269_2014.pdf, Article 2 | H13: Einfrieren, Bereitstellungsverbot
... A31: Q30 | B31: Payments | C31: A customer reports an unauthorised card payment. What must the bank do, and how far is the customer liable? | D31: Fact | E31: 2 | F31: The bank must refund the amount immediately, at the latest by the end of the business day after notification (unless it has reasonable grounds to suspect fraud and reports them). The customer is liable up to EUR 50 for lost, stolen or misused instruments, fully only in case of fraud or gross negligence. The customer must report within 13 months. | G31: 49_BGB.pdf, sections 675u, 675v, 676b | H31: nicht autorisierter Zahlungsvorgang, Erstattung, 50 Euro
A32: Q31 | B32: Out of scope | C32: What is the ECB's current deposit facility rate? | D32: Out of scope | E32: 1 | F32: Not covered by the corpus. The assistant must say it cannot answer from the available documents and must not state a rate. | G32: None
A33: Q32 | B33: Out of scope | C33: What lending approval limits apply to branch managers at our bank? | D33: Out of scope | E33: 1 | F33: Institution-specific, not covered by the corpus. The assistant should say so, may point out that MaRisk requires a clear allocation of competences, but must not invent limits. | G33: None (optional reference: 21_MaRisk_06_2026.pdf)

Sheet Scoring
A1: Scoring
A2: Enter the assistant's answer and your score in the yellow cells. Score: 1, 0.5 or 0. Sources OK: Y or N.
B3: Questions scored | C3: =COUNT(E7:E38) -> 0 | D3: Correct sources | E3: =IF(COUNTA(F7:F38)=0,0,COUNTIF(F7:F38,"Y")/COUNTA(F7:F38)) -> 0
B4: Accuracy (target 85%) | C4: =IF(COUNT(E7:E38)=0,0,SUM(E7:E38)/COUNT(E7:E38)) -> 0
A6: ID | B6: Question | C6: Assistant answer | D6: Cited sources | E6: Score (1 / 0.5 / 0) | F6: Sources OK (Y/N) | G6: Notes
A7: ='Question set'!A2 -> Q01 | B7: ='Question set'!C2 -> Under the German Money Laundering Act, in which situations must a bank carry out customer due diligence?
A8: ='Question set'!A3 -> Q02 | B8: ='Question set'!C3 -> When is a natural person considered the beneficial owner of a company under the GwG?
A9: ='Question set'!A4 -> Q03 | B9: ='Question set'!C4 -> How long must a bank retain the records it collects under its due diligence obligations?
A10: ='Question set'!A5 -> Q04 | B10: ='Question set'!C5 -> A bank employee suspects that a customer payment is linked to money laundering. To whom must the bank report, and how quickly?
A11: ='Question set'!A6 -> Q05 | B11: ='Question set'!C6 -> After filing a suspicious activity report, may the bank execute the reported transaction straight away?
A12: ='Question set'!A7 -> Q06 | B12: ='Question set'!C7 -> May a bank tell its customer that it has filed a suspicious activity report about them?
A13: ='Question set'!A8 -> Q07 | B13: ='Question set'!C8 -> Which enhanced due diligence measures apply when the customer is a politically exposed person (PEP)?
A14: ='Question set'!A9 -> Q08 | B14: ='Question set'!C9 -> Which document determines whether a country is a high-risk third country, and what does that mean for a German bank?
A15: ='Question set'!A10 -> Q09 | B15: ='Question set'!C10 -> Who in a bank must be responsible for AML/CFT, and at which level?
A16: ='Question set'!A11 -> Q10 | B16: ='Question set'!C11 -> What must a bank do before it starts using a remote customer onboarding solution?
A17: ='Question set'!A12 -> Q11 | B17: ='Question set'!C12 -> Which information about the payer and the payee must accompany a transfer of funds?
A18: ='Question set'!A13 -> Q12 | B18: ='Question set'!C13 -> What does an asset freeze under the EU Russia/Ukraine sanctions mean for a bank holding an account of a listed person?
... A38: ='Question set'!A33 -> Q32 | B38: ='Question set'!C33 -> What lending approval limits apply to branch managers at our bank?
